{
  "$type": "RPG.GameCore.RtLevelGroupInfo",
  "GroupName": "MainMission2022104_15",
  "Category": "Mission",
  "LevelGraph": "Config/Level/GroupGraph/F20241001/Group_F20241001_G40.json",
  "AreaAnchorName": "LevelArea_P20241_F20241001_G40",
  "SaveType": "Reset",
  "OwnerMainMissionID": 2022104,
  "ValueSource": {},
  "ConflictIDList": [],
  "IsHoyoGroup": true,
  "StreamingTemplateType": "None",
  "ConflictWhiteList": [],
  "TagContainer": {
    "List": [
      {
        "Tag": "Group.TrailblazeContinuance.240to250XianZhou",
        "TagHash": -357934452
      }
    ]
  },
  "AnchorList": [
    {
      "ID": 1,
      "PosX": 30.450000762939453,
      "PosY": -170.77000427246094,
      "PosZ": -1.399999976158142,
      "Name": "Anchor1",
      "RotY": 182.60000610351562,
      "Usage": "Actor"
    },
    {
      "ID": 2,
      "PosX": 20.841999053955078,
      "PosY": -170.6468963623047,
      "PosZ": -16.92099952697754,
      "Name": "Anchor2",
      "RotY": 316.5
    }
  ],
  "MonsterList": [],
  "PropList": [
    {
      "ID": 300001,
      "PosX": 18.358749389648438,
      "PosY": -170.43809509277344,
      "PosZ": -17.690000534057617,
      "Name": "Prop1",
      "PropID": 100,
      "ValueSource": {},
      "CampID": 4,
      "CustomTriggerMap": {},
      "CustomTriggerMapV2": {
        "MissionTrigger": {
          "Radius": 4.0,
          "PointList": []
        }
      },
      "StateConfigs": [],
      "DialogueGroups": [],
      "TalkDialogGroupIDList": [],
      "ServerInteractVerificationIDList": [],
      "CameraCenterEntityList": [],
      "SpawnConfig": {
        "EntitySpawnConfig": {}
      }
    },
    {
      "ID": 300002,
      "PosX": 26.850000381469727,
      "PosY": -170.77000427246094,
      "PosZ": -14.170000076293945,
      "Name": "Prop2",
      "RotY": 46.72999954223633,
      "PropID": 100,
      "ValueSource": {},
      "CampID": 4,
      "CustomTriggerMap": {},
      "CustomTriggerMapV2": {
        "MissionTrigger": {
          "Shape": "Box",
          "Radius": 2.0,
          "DimX": 17.729999542236328,
          "DimY": 1.0,
          "DimZ": 22.899999618530273,
          "PointList": []
        }
      },
      "StateConfigs": [],
      "DialogueGroups": [],
      "TalkDialogGroupIDList": [],
      "ServerInteractVerificationIDList": [],
      "CameraCenterEntityList": [],
      "SpawnConfig": {
        "EntitySpawnConfig": {}
      }
    },
    {
      "ID": 300003,
      "PosX": 18.195730209350586,
      "PosY": -170.4954071044922,
      "PosZ": -18.132099151611328,
      "Name": "Prop3",
      "PropID": 100,
      "LoadOnInitial": false,
      "ValueSource": {},
      "Trigger": {
        "Radius": 1.5,
        "DimX": 1.0,
        "DimY": 1.0,
        "DimZ": 1.0,
        "PointList": []
      },
      "CampID": 4,
      "CustomTriggerMap": {},
      "CustomTriggerMapV2": {},
      "StateConfigs": [],
      "DialogueGroups": [],
      "TalkDialogGroupIDList": [],
      "ServerInteractVerificationIDList": [],
      "Dialog": {
        "LevelGraph": "Config/Level/PropDialogue/P20241/F20241001_G40/DialogueMain_F20241001_G40_P300003.json",
        "PackList": []
      },
      "CameraCenterEntityList": [],
      "SpawnConfig": {
        "EntitySpawnConfig": {}
      }
    }
  ],
  "DistrictList": [],
  "WaypointList": [],
  "PathwayList": [],
  "BattleAreaList": [],
  "NPCList": [
    {
      "ID": 400001,
      "PosX": 27.000999450683594,
      "PosY": -170.6468963623047,
      "PosZ": -5.761000156402588,
      "Name": "NPC1",
      "RotY": 191.49000549316406,
      "NPCID": 1208,
      "ValueSource": {},
      "SOConfig": {
        "InstanceID": 1
      },
      "DialogueGroups": [],
      "ServerInteractVerificationIDList": [],
      "BoardShowList": [],
      "TalkDialogGroupIDList": [],
      "DefaultIdleFreeStyleMotionID": 312140000,
      "InitialHiddenNodeList": [],
      "CameraCenterEntityList": [],
      "SpawnConfig": {
        "EntitySpawnConfig": {}
      },
      "TriggerValidGuest": {}
    },
    {
      "ID": 400002,
      "PosX": 16.742000579833984,
      "PosY": -170.6468963623047,
      "PosZ": -16.559999465942383,
      "Name": "NPC2",
      "RotY": 314.79998779296875,
      "NPCID": 3011,
      "LoadOnInitial": false,
      "ValueSource": {},
      "DialogueGroups": [],
      "ServerInteractVerificationIDList": [],
      "DefaultLookAtMode": "Closed",
      "BoardShowList": [],
      "TalkDialogGroupIDList": [],
      "DefaultIdleFreeStyleMotionID": 900070293,
      "InitialHiddenNodeList": [],
      "CameraCenterEntityList": [],
      "SpawnConfig": {
        "EntitySpawnConfig": {}
      },
      "TriggerValidGuest": {}
    },
    {
      "ID": 400003,
      "PosX": 36.61899948120117,
      "PosY": -170.77000427246094,
      "PosZ": -4.175004005432129,
      "Name": "NPC3",
      "RotY": 270.0,
      "NPCID": 1223,
      "ValueSource": {},
      "StaticNPC": true,
      "DialogueGroups": [],
      "ServerInteractVerificationIDList": [],
      "BoardShowList": [],
      "TalkDialogGroupIDList": [],
      "DefaultIdleFreeStyleMotionID": 312230441,
      "InitialHiddenNodeList": [],
      "Dialog": {
        "LevelGraph": "Config/Level/NPCDialogue/P20241/F20241001_G40/DialogueMain_F20241001_G40_N400003.json",
        "PackList": []
      },
      "CameraCenterEntityList": [],
      "SpawnConfig": {
        "EntitySpawnConfig": {}
      },
      "TriggerValidGuest": {}
    }
  ],
  "CrowdList": [],
  "PedestrianList": [],
  "AudienceList": [],
  "SmartObjectList": [
    {
      "ID": 1,
      "PosX": 25.531400680541992,
      "PosY": -170.6468963623047,
      "PosZ": -12.648420333862305,
      "Name": "SmartObject1",
      "SlotList": [
        {
          "PointList": [
            {
              "PosX": -4.650000095367432,
              "PosZ": -4.230000019073486,
              "RotY": 316.5,
              "RestartMode": "RestartFromSO",
              "RootTask": {
                "$type": "RPG.GameCore.SO_Sequence",
                "WaitMessages": [],
                "Tasks": [
                  {
                    "$type": "RPG.GameCore.SO_MoveTo",
                    "MoveStance": "Walk"
                  },
                  {
                    "$type": "RPG.GameCore.SO_PlayFreeStyle",
                    "StoryAvatarID": "NPC_Avatar_Maid_Xueyi_00",
                    "StoryMotionID": 312140219,
                    "ForceStart": false
                  },
                  {
                    "$type": "RPG.GameCore.SO_TriggerGroupEvent",
                    "EventName": "MissionTalk_222142002"
                  }
                ]
              }
            }
          ]
        }
      ],
      "CommonPointList": []
    }
  ]
}