{
  "OnStartSequece": [
    {
      "TaskList": [
        {
          "$type": "RPG.GameCore.LevelPerformanceInitialize",
          "PerformanceType": "E",
          "HideMunicipalCrowd": false,
          "HideMunicipalPedestrian": false,
          "UseNewStreamingSourceType": false
        },
        {
          "$type": "RPG.GameCore.PlayAndWaitSimpleTalk",
          "SimpleTalkList": [
            {
              "TextSpeed": 0.0,
              "TalkSentenceID": 103415601,
              "ProtectTime": 0.0
            },
            {
              "TextSpeed": 0.0,
              "TalkSentenceID": 103415602,
              "ProtectTime": 0.0
            },
            {
              "TextSpeed": 0.0,
              "TalkSentenceID": 103415603,
              "ProtectTime": 0.0
            },
            {
              "TextSpeed": 0.0,
              "TalkSentenceID": 103415604,
              "ProtectTime": 0.0
            },
            {
              "TextSpeed": 0.0,
              "TalkSentenceID": 103415605,
              "ProtectTime": 0.0
            },
            {
              "TextSpeed": 0.0,
              "TalkSentenceID": 103415606,
              "ProtectTime": 0.0
            }
          ]
        },
        {
          "$type": "RPG.GameCore.EndPerformance"
        }
      ]
    },
    {
      "TaskList": [
        {
          "$type": "RPG.GameCore.WaitPerformanceEnd"
        },
        {
          "$type": "RPG.GameCore.FinishLevelGraph"
        }
      ]
    }
  ]
}