{
  "$type": "RPG.GameCore.RtLevelGroupInfo",
  "GroupName": "RogueOrigin_BaseCommon",
  "Category": "Custom",
  "AreaAnchorName": "LevelArea_P81221_F81221001_G57",
  "LoadSide": "Server",
  "ValueSource": {},
  "ConflictIDList": [],
  "IsHoyoGroup": true,
  "ConflictWhiteList": [],
  "AnchorList": [
    {
      "ID": 1,
      "PosX": 133.3800048828125,
      "PosY": -1.7843070030212402,
      "PosZ": 65.79000091552734,
      "Name": "Anchor1",
      "RotY": 180.0
    }
  ],
  "MonsterList": [],
  "PropList": [
    {
      "ID": 300001,
      "PosX": 136.3800048828125,
      "PosY": -3.5114009380340576,
      "PosZ": 21.440000534057617,
      "Name": "Door1",
      "RotY": 270.0000915527344,
      "PropID": 1000,
      "IsOverrideInitLevelGraph": true,
      "InitLevelGraph": "Config/Level/Maze/MazeRogue/Maze_Rogue_Prop_Door.json",
      "ValueSource": {},
      "Trigger": {
        "Radius": 2.0,
        "DimX": 1.0,
        "DimY": 1.0,
        "DimZ": 1.0,
        "PointList": []
      },
      "CampID": 4,
      "CustomTriggerMap": {},
      "CustomTriggerMapV2": {},
      "DialogueGroups": [],
      "TalkDialogGroupIDList": [],
      "ServerInteractVerificationIDList": [],
      "Dialog": {
        "PackList": []
      },
      "TriggerValidGuest": {}
    },
    {
      "ID": 300002,
      "PosX": 130.3800048828125,
      "PosY": -3.511401891708374,
      "PosZ": 21.440000534057617,
      "Name": "Door2",
      "RotY": 180.0,
      "PropID": 1000,
      "IsOverrideInitLevelGraph": true,
      "InitLevelGraph": "Config/Level/Maze/MazeRogue/Maze_Rogue_Prop_Door.json",
      "ValueSource": {},
      "Trigger": {
        "Radius": 2.0,
        "DimX": 1.0,
        "DimY": 1.0,
        "DimZ": 1.0,
        "PointList": []
      },
      "CampID": 4,
      "CustomTriggerMap": {},
      "CustomTriggerMapV2": {},
      "DialogueGroups": [],
      "TalkDialogGroupIDList": [],
      "ServerInteractVerificationIDList": [],
      "Dialog": {
        "PackList": []
      },
      "TriggerValidGuest": {}
    },
    {
      "ID": 300003,
      "PosX": 136.3800048828125,
      "PosY": -1.7843049764633179,
      "PosZ": 60.49000930786133,
      "Name": "Destruct",
      "RotY": 180.0,
      "PropID": 102008,
      "IsOverrideInitLevelGraph": true,
      "ValueSource": {},
      "CampID": 4,
      "EventID": 80210001,
      "CustomTriggerMap": {},
      "CustomTriggerMapV2": {},
      "DialogueGroups": [],
      "TalkDialogGroupIDList": [],
      "ServerInteractVerificationIDList": []
    },
    {
      "ID": 300004,
      "PosX": 130.3800048828125,
      "PosY": -1.7843049764633179,
      "PosZ": 55.900001525878906,
      "Name": "Destruct",
      "RotY": 180.0,
      "PropID": 102008,
      "IsOverrideInitLevelGraph": true,
      "ValueSource": {},
      "CampID": 4,
      "EventID": 80210001,
      "CustomTriggerMap": {},
      "CustomTriggerMapV2": {},
      "DialogueGroups": [],
      "TalkDialogGroupIDList": [],
      "ServerInteractVerificationIDList": []
    },
    {
      "ID": 300005,
      "PosX": 136.3800048828125,
      "PosY": -1.7843029499053955,
      "PosZ": 51.560001373291016,
      "Name": "Destruct",
      "RotY": 180.0,
      "PropID": 102008,
      "IsOverrideInitLevelGraph": true,
      "ValueSource": {},
      "CampID": 4,
      "EventID": 80210001,
      "CustomTriggerMap": {},
      "CustomTriggerMapV2": {},
      "DialogueGroups": [],
      "TalkDialogGroupIDList": [],
      "ServerInteractVerificationIDList": []
    },
    {
      "ID": 300006,
      "PosX": 136.3800048828125,
      "PosY": -1.7843049764633179,
      "PosZ": 59.650001525878906,
      "Name": "Destruct",
      "RotY": 180.0,
      "PropID": 102008,
      "IsOverrideInitLevelGraph": true,
      "ValueSource": {},
      "CampID": 4,
      "EventID": 80210001,
      "CustomTriggerMap": {},
      "CustomTriggerMapV2": {},
      "DialogueGroups": [],
      "TalkDialogGroupIDList": [],
      "ServerInteractVerificationIDList": []
    },
    {
      "ID": 300007,
      "PosX": 130.3800048828125,
      "PosY": -1.7843040227890015,
      "PosZ": 55.11899948120117,
      "Name": "Destruct",
      "RotY": 180.0,
      "PropID": 102008,
      "IsOverrideInitLevelGraph": true,
      "ValueSource": {},
      "CampID": 4,
      "EventID": 80210001,
      "CustomTriggerMap": {},
      "CustomTriggerMapV2": {},
      "DialogueGroups": [],
      "TalkDialogGroupIDList": [],
      "ServerInteractVerificationIDList": []
    },
    {
      "ID": 300008,
      "PosX": 136.3800048828125,
      "PosY": -1.7843029499053955,
      "PosZ": 50.689998626708984,
      "Name": "Destruct",
      "RotY": 180.0,
      "PropID": 102008,
      "IsOverrideInitLevelGraph": true,
      "ValueSource": {},
      "CampID": 4,
      "EventID": 80210001,
      "CustomTriggerMap": {},
      "CustomTriggerMapV2": {},
      "DialogueGroups": [],
      "TalkDialogGroupIDList": [],
      "ServerInteractVerificationIDList": []
    }
  ],
  "DistrictList": [],
  "WaypointList": [],
  "PathwayList": [],
  "BattleAreaList": [],
  "NPCList": [],
  "CrowdList": [],
  "PedestrianList": [],
  "SmartObjectList": []
}