{
  "$type": "RPG.GameCore.RtLevelGroupInfo",
  "GroupName": "MainMission4340134_06",
  "Category": "Mission",
  "LevelGraph": "Config/Level/GroupGraph/F10306001/Group_F10306001_G312.json",
  "AreaAnchorName": "LevelArea_P10306_F10306001_G312",
  "SaveType": "Reset",
  "OwnerMainMissionID": 4340134,
  "ValueSource": {},
  "ConflictIDList": [],
  "IsHoyoGroup": true,
  "ConflictWhiteList": [],
  "AnchorList": [
    {
      "ID": 1,
      "PosX": 41.540000915527344,
      "PosY": 4.894750118255615,
      "PosZ": 41.20000076293945,
      "Name": "Anchor1",
      "RotY": 316.05218505859375,
      "Usage": "Actor"
    }
  ],
  "MonsterList": [],
  "PropList": [],
  "DistrictList": [],
  "WaypointList": [],
  "PathwayList": [],
  "BattleAreaList": [],
  "NPCList": [
    {
      "ID": 400001,
      "PosX": 47.79999923706055,
      "PosY": 5.619999885559082,
      "PosZ": 37.409000396728516,
      "Name": "NPC1",
      "RotY": 233.35360717773438,
      "NPCID": 2309,
      "ValueSource": {},
      "StaticNPC": true,
      "DialogueGroups": [],
      "ServerInteractVerificationIDList": [],
      "DefaultLookAtMode": "Closed",
      "BoardShowList": [],
      "TalkDialogGroupIDList": [],
      "DefaultIdleFreeStyleMotionID": 200680000,
      "InitialHiddenNodeList": [],
      "DialogueTriggerSkipSpecifiedFakeAvatarList": [],
      "OverrideReplaceMaterialKeyList": [],
      "CameraCenterEntityList": [],
      "CameraConfig": {},
      "SpawnConfig": {
        "EntitySpawnConfig": {}
      },
      "TriggerValidGuest": {}
    },
    {
      "ID": 400002,
      "PosX": 54.77000045776367,
      "PosY": 5.7769999504089355,
      "PosZ": 30.89900016784668,
      "Name": "NPC2",
      "RotY": 252.41110229492188,
      "NPCID": 2303,
      "ValueSource": {},
      "StaticNPC": true,
      "DialogueGroups": [],
      "ServerInteractVerificationIDList": [],
      "DefaultLookAtMode": "Closed",
      "BoardShowList": [],
      "TalkDialogGroupIDList": [],
      "DefaultIdleFreeStyleMotionID": 200310000,
      "InitialHiddenNodeList": [],
      "DialogueTriggerSkipSpecifiedFakeAvatarList": [],
      "OverrideReplaceMaterialKeyList": [],
      "CameraCenterEntityList": [],
      "CameraConfig": {},
      "SpawnConfig": {
        "EntitySpawnConfig": {}
      },
      "TriggerValidGuest": {}
    },
    {
      "ID": 400003,
      "PosX": 50.98699951171875,
      "PosY": 5.433000087738037,
      "PosZ": 37.48899841308594,
      "Name": "NPC3",
      "RotY": 241.08670043945312,
      "NPCID": 2307,
      "ValueSource": {},
      "StaticNPC": true,
      "DialogueGroups": [],
      "ServerInteractVerificationIDList": [],
      "DefaultLookAtMode": "Closed",
      "BoardShowList": [],
      "TalkDialogGroupIDList": [],
      "DefaultIdleFreeStyleMotionID": 200570000,
      "InitialHiddenNodeList": [],
      "DialogueTriggerSkipSpecifiedFakeAvatarList": [],
      "OverrideReplaceMaterialKeyList": [],
      "CameraCenterEntityList": [],
      "CameraConfig": {},
      "SpawnConfig": {
        "EntitySpawnConfig": {}
      },
      "TriggerValidGuest": {}
    },
    {
      "ID": 400004,
      "PosX": 49.51900100708008,
      "PosY": 5.605999946594238,
      "PosZ": 34.23699951171875,
      "Name": "NPC4",
      "RotY": 241.30580139160156,
      "NPCID": 3025,
      "ValueSource": {},
      "StaticNPC": true,
      "DialogueGroups": [],
      "ServerInteractVerificationIDList": [],
      "DefaultLookAtMode": "Closed",
      "BoardShowList": [],
      "TalkDialogGroupIDList": [],
      "DefaultIdleFreeStyleMotionID": 200690000,
      "InitialHiddenNodeList": [],
      "DialogueTriggerSkipSpecifiedFakeAvatarList": [],
      "OverrideReplaceMaterialKeyList": [],
      "CameraCenterEntityList": [],
      "CameraConfig": {},
      "SpawnConfig": {
        "EntitySpawnConfig": {}
      },
      "TriggerValidGuest": {}
    },
    {
      "ID": 400005,
      "PosX": 48.04399871826172,
      "PosY": 5.7779998779296875,
      "PosZ": 42.52000045776367,
      "Name": "NPC5",
      "RotY": 241.30580139160156,
      "NPCID": 2310,
      "ValueSource": {},
      "StaticNPC": true,
      "DialogueGroups": [],
      "ServerInteractVerificationIDList": [],
      "DefaultLookAtMode": "Closed",
      "BoardShowList": [],
      "TalkDialogGroupIDList": [],
      "DefaultIdleFreeStyleMotionID": 200380000,
      "InitialHiddenNodeList": [],
      "DialogueTriggerSkipSpecifiedFakeAvatarList": [],
      "OverrideReplaceMaterialKeyList": [],
      "CameraCenterEntityList": [],
      "CameraConfig": {},
      "SpawnConfig": {
        "EntitySpawnConfig": {}
      },
      "TriggerValidGuest": {}
    }
  ],
  "CrowdList": [],
  "PedestrianList": [],
  "PedestrianV2List": [],
  "AudienceList": [],
  "SmartObjectList": [],
  "CurveList": [],
  "LittleGameList": []
}