{
  "$type": "RPG.GameCore.RtLevelGroupInfo",
  "GroupName": "NPC",
  "LevelGraph": "Config/Level/GroupGraph/F40104021/Group_F40104021_G6.json",
  "AreaAnchorName": "LevelArea_P40104_F40104021_G6",
  "SaveType": "Reset",
  "SavedValueCondition": {
    "Conditions": [],
    "Operation": "And"
  },
  "LoadOnInitial": true,
  "ValueSource": {},
  "ConflictIDList": [],
  "IsHoyoGroup": true,
  "ConflictWhiteList": [],
  "AnchorList": [],
  "MonsterList": [],
  "PropList": [],
  "DistrictList": [
    {
      "ID": 1,
      "PosX": 69.41000366210938,
      "PosY": -18.06399917602539,
      "PosZ": 36.150001525878906,
      "Name": "District1",
      "Trigger": {
        "Radius": 3.0,
        "DimX": 1.0,
        "DimY": 1.0,
        "DimZ": 1.0,
        "PointList": []
      },
      "DistrictType": "Level",
      "ValueSource": {}
    },
    {
      "ID": 2,
      "PosX": 69.6500015258789,
      "PosY": -18.06399917602539,
      "PosZ": 44.91999816894531,
      "Name": "District2",
      "Trigger": {
        "Radius": 3.0,
        "DimX": 1.0,
        "DimY": 1.0,
        "DimZ": 1.0,
        "PointList": []
      },
      "DistrictType": "Level",
      "ValueSource": {}
    }
  ],
  "WaypointList": [],
  "PathwayList": [],
  "BattleAreaList": [],
  "NPCList": [
    {
      "ID": 400001,
      "PosX": 69.41000366210938,
      "PosY": -18.06399917602539,
      "PosZ": 36.150001525878906,
      "Name": "NPC15-StoryGhost",
      "RotY": 49.31159973144531,
      "NPCID": 12135,
      "ValueSource": {},
      "DialogueGroups": [],
      "ServerInteractVerificationIDList": [],
      "BoardShowList": [
        8
      ],
      "TalkDialogGroupIDList": [],
      "DefaultIdleFreeStyleMotionID": 100010000,
      "InitialHiddenNodeList": [],
      "OverrideReplaceMaterialKeyList": [
        "NPC_W2_Male_27_StoryGhost"
      ],
      "CameraCenterEntityList": [],
      "SpawnConfig": {
        "EntitySpawnConfig": {}
      },
      "TriggerValidGuest": {}
    },
    {
      "ID": 400007,
      "PosX": 69.6500015258789,
      "PosY": -18.06399917602539,
      "PosZ": 44.91999816894531,
      "Name": "NPC21-StoryGhost",
      "RotY": 262.87091064453125,
      "NPCID": 12251,
      "ValueSource": {},
      "DialogueGroups": [],
      "ServerInteractVerificationIDList": [],
      "BoardShowList": [
        8
      ],
      "TalkDialogGroupIDList": [],
      "DefaultIdleFreeStyleMotionID": 100020000,
      "InitialHiddenNodeList": [],
      "OverrideReplaceMaterialKeyList": [
        "NPC_W2_Lady_49_StoryGhost"
      ],
      "CameraCenterEntityList": [],
      "SpawnConfig": {
        "EntitySpawnConfig": {}
      },
      "TriggerValidGuest": {}
    }
  ],
  "CrowdList": [],
  "PedestrianList": [],
  "AudienceList": [],
  "SmartObjectList": [],
  "CurveList": [],
  "LittleGameList": []
}