{
  "$type": "RPG.GameCore.RtLevelGroupInfo",
  "GroupName": "R2_Pose2_3rd_Wolf_Chests",
  "AreaAnchorName": "LevelArea_P20322_F20322001_G104",
  "SavedValueCondition": {
    "Conditions": [
      {
        "SavedValueName": "ChallengeNum_Host",
        "Value": 3
      }
    ],
    "Operation": "And"
  },
  "LoadSide": "Server",
  "LoadOnInitial": true,
  "ValueSource": {},
  "ConflictIDList": [],
  "IsHoyoGroup": true,
  "HoYoGroupType": "Container",
  "ConflictWhiteList": [],
  "TagContainer": {
    "List": [
      {
        "Tag": "Group.Level.TreasureChest",
        "TagHash": 1042911019
      }
    ]
  },
  "AnchorList": [],
  "MonsterList": [],
  "PropList": [
    {
      "ID": 300001,
      "PosX": 58.50699996948242,
      "PosY": 94.34398651123047,
      "PosZ": 102.5459976196289,
      "Name": "Prop1",
      "RotY": 89.9999771118164,
      "RotX": 0.0001539999939268455,
      "RotZ": 89.9999771118164,
      "PropID": 60303,
      "ValueSource": {},
      "CampID": 4,
      "State": "ChestClosed",
      "CustomTriggerMap": {},
      "CustomTriggerMapV2": {},
      "StateConfigs": [],
      "ChestID": 20322621,
      "DialogueGroups": [],
      "TalkDialogGroupIDList": [],
      "ServerInteractVerificationIDList": [],
      "DialogueTriggerSkipSpecifiedFakeAvatarList": [],
      "OverrideTriggerValidGuestConfig": true,
      "TriggerValidGuest": {
        "FakePlayer": true
      },
      "CameraCenterEntityList": [],
      "CameraConfig": {},
      "SpawnConfig": {
        "EntitySpawnConfig": {}
      }
    },
    {
      "ID": 300002,
      "PosX": 71.94599914550781,
      "PosY": 76.343017578125,
      "PosZ": 102.5459976196289,
      "Name": "Prop2",
      "RotY": 89.99996185302734,
      "RotX": 0.0001429999974789098,
      "RotZ": 89.99994659423828,
      "PropID": 60301,
      "ValueSource": {},
      "CampID": 4,
      "State": "ChestClosed",
      "CustomTriggerMap": {},
      "CustomTriggerMapV2": {},
      "StateConfigs": [],
      "ChestID": 20322620,
      "DialogueGroups": [],
      "TalkDialogGroupIDList": [],
      "ServerInteractVerificationIDList": [],
      "DialogueTriggerSkipSpecifiedFakeAvatarList": [],
      "OverrideTriggerValidGuestConfig": true,
      "TriggerValidGuest": {
        "FakePlayer": true
      },
      "CameraCenterEntityList": [],
      "CameraConfig": {},
      "SpawnConfig": {
        "EntitySpawnConfig": {}
      }
    }
  ],
  "DistrictList": [],
  "WaypointList": [],
  "PathwayList": [],
  "BattleAreaList": [],
  "NPCList": [],
  "CrowdList": [],
  "PedestrianList": [],
  "PedestrianV2List": [],
  "AudienceList": [],
  "SmartObjectList": [],
  "CurveList": [],
  "LittleGameList": []
}