{
  "$type": "RPG.GameCore.RtLevelGroupInfo",
  "GroupName": "Investigative",
  "AreaAnchorName": "LevelArea_P10101_F10101002_G2",
  "LoadOnInitial": true,
  "AnchorList": [],
  "MonsterList": [],
  "PropList": [
    {
      "ID": 300001,
      "PosX": -4.179999828338623,
      "PosY": 0.5176810026168823,
      "PosZ": -10.100000381469727,
      "Name": "Prop1",
      "PropID": 120,
      "IsOverrideInitLevelGraph": true,
      "Trigger": {
        "Radius": 2.5,
        "DimX": 1.0,
        "DimY": 1.0,
        "DimZ": 1.0
      },
      "CampID": 4,
      "OverrideHintRange": 0.0,
      "CustomTriggerMap": {},
      "DialogueGroups": [],
      "TalkDialogGroupIDList": [
        101019782,
        101019783,
        101019784
      ],
      "TalkChosenType": "random",
      "ServerInteractVerificationIDList": []
    },
    {
      "ID": 300002,
      "PosX": 0.0020000000949949026,
      "PosY": 0.5176810026168823,
      "PosZ": -5.02400016784668,
      "Name": "Prop2",
      "PropID": 120,
      "IsOverrideInitLevelGraph": true,
      "Trigger": {
        "Shape": "Box",
        "Radius": 3.0,
        "DimX": 5.0,
        "DimY": 2.0,
        "DimZ": 2.5
      },
      "CampID": 4,
      "OverrideHintRange": 0.0,
      "CustomTriggerMap": {},
      "DialogueGroups": [],
      "TalkDialogGroupIDList": [
        101019785,
        101019786,
        101019787
      ],
      "TalkChosenType": "random",
      "ServerInteractVerificationIDList": []
    },
    {
      "ID": 300003,
      "PosX": 3.7720000743865967,
      "PosY": 0.5176810026168823,
      "PosZ": -10.265999794006348,
      "Name": "Prop3",
      "PropID": 120,
      "IsOverrideInitLevelGraph": true,
      "Trigger": {
        "Radius": 1.0,
        "DimX": 5.0,
        "DimY": 2.0,
        "DimZ": 2.5
      },
      "CampID": 4,
      "OverrideHintRange": 0.0,
      "CustomTriggerMap": {},
      "DialogueGroups": [],
      "TalkDialogGroupIDList": [
        101019788
      ],
      "TalkChosenType": "loop",
      "ServerInteractVerificationIDList": []
    },
    {
      "ID": 300004,
      "PosX": 9.168000221252441,
      "PosY": 0.5176810026168823,
      "PosZ": -7.131999969482422,
      "Name": "Prop4",
      "PropID": 120,
      "IsOverrideInitLevelGraph": true,
      "Trigger": {
        "Radius": 1.0,
        "DimX": 5.0,
        "DimY": 2.0,
        "DimZ": 2.5
      },
      "CampID": 4,
      "OverrideHintRange": 0.0,
      "CustomTriggerMap": {},
      "DialogueGroups": [],
      "TalkDialogGroupIDList": [
        101019789
      ],
      "TalkChosenType": "loop",
      "ServerInteractVerificationIDList": []
    },
    {
      "ID": 300005,
      "PosX": 10.843999862670898,
      "PosY": 0.5176810026168823,
      "PosZ": 2.8559999465942383,
      "Name": "Prop5",
      "PropID": 120,
      "IsOverrideInitLevelGraph": true,
      "Trigger": {
        "Shape": "Box",
        "Radius": 1.0,
        "DimX": 5.0,
        "DimY": 2.0,
        "DimZ": 7.5
      },
      "CampID": 4,
      "OverrideHintRange": 0.0,
      "CustomTriggerMap": {},
      "DialogueGroups": [],
      "TalkDialogGroupIDList": [
        101019790,
        101019791,
        101019792
      ],
      "TalkChosenType": "random",
      "ServerInteractVerificationIDList": []
    },
    {
      "ID": 300006,
      "PosX": 9.720000267028809,
      "PosY": 0.5176810026168823,
      "PosZ": 12.529999732971191,
      "Name": "Prop6",
      "PropID": 120,
      "IsOverrideInitLevelGraph": true,
      "Trigger": {
        "Shape": "Box",
        "Radius": 2.0,
        "DimX": 4.0,
        "DimY": 2.0,
        "DimZ": 4.0
      },
      "CampID": 4,
      "OverrideHintRange": 0.0,
      "CustomTriggerMap": {},
      "DialogueGroups": [],
      "TalkDialogGroupIDList": [
        101019790,
        101019791,
        101019792
      ],
      "TalkChosenType": "random",
      "ServerInteractVerificationIDList": []
    },
    {
      "ID": 300007,
      "PosX": -9.892000198364258,
      "PosY": 0.5176810026168823,
      "PosZ": 8.684000015258789,
      "Name": "Prop7",
      "PropID": 120,
      "IsOverrideInitLevelGraph": true,
      "Trigger": {
        "Shape": "Box",
        "Radius": 2.0,
        "DimX": 4.0,
        "DimY": 2.0,
        "DimZ": 5.0
      },
      "CampID": 4,
      "OverrideHintRange": 0.0,
      "CustomTriggerMap": {},
      "DialogueGroups": [],
      "TalkDialogGroupIDList": [
        101019790,
        101019791,
        101019792
      ],
      "TalkChosenType": "random",
      "ServerInteractVerificationIDList": []
    },
    {
      "ID": 300008,
      "PosX": -10.86400032043457,
      "PosY": 0.5176810026168823,
      "PosZ": 0.8799999952316284,
      "Name": "Prop8",
      "PropID": 120,
      "IsOverrideInitLevelGraph": true,
      "Trigger": {
        "Shape": "Box",
        "Radius": 2.0,
        "DimX": 4.0,
        "DimY": 2.0,
        "DimZ": 3.5
      },
      "CampID": 4,
      "OverrideHintRange": 0.0,
      "CustomTriggerMap": {},
      "DialogueGroups": [],
      "TalkDialogGroupIDList": [
        101019790,
        101019791,
        101019792
      ],
      "TalkChosenType": "random",
      "ServerInteractVerificationIDList": []
    },
    {
      "ID": 300009,
      "PosX": -9.979999542236328,
      "PosY": 0.5176810026168823,
      "PosZ": -5.039999961853027,
      "Name": "Prop9",
      "PropID": 120,
      "IsOverrideInitLevelGraph": true,
      "Trigger": {
        "Shape": "Box",
        "Radius": 2.0,
        "DimX": 2.0,
        "DimY": 2.0,
        "DimZ": 3.0
      },
      "CampID": 4,
      "OverrideHintRange": 0.0,
      "CustomTriggerMap": {},
      "DialogueGroups": [],
      "TalkDialogGroupIDList": [
        101019793
      ],
      "TalkChosenType": "loop",
      "ServerInteractVerificationIDList": []
    },
    {
      "ID": 300010,
      "PosX": 9.90999984741211,
      "PosY": 0.5176810026168823,
      "PosZ": -5.039999961853027,
      "Name": "Prop10",
      "PropID": 120,
      "IsOverrideInitLevelGraph": true,
      "Trigger": {
        "Shape": "Box",
        "Radius": 2.0,
        "DimX": 2.0,
        "DimY": 2.0,
        "DimZ": 3.0
      },
      "CampID": 4,
      "OverrideHintRange": 0.0,
      "CustomTriggerMap": {},
      "DialogueGroups": [],
      "TalkDialogGroupIDList": [
        101019793
      ],
      "TalkChosenType": "loop",
      "ServerInteractVerificationIDList": []
    },
    {
      "ID": 300011,
      "PosX": 7.215000152587891,
      "PosY": 0.5176810026168823,
      "PosZ": 14.35200023651123,
      "Name": "Prop11",
      "RotY": 90.0,
      "PropID": 120,
      "IsOverrideInitLevelGraph": true,
      "Trigger": {
        "Shape": "Box",
        "Radius": 2.0,
        "DimX": 2.0,
        "DimY": 2.0,
        "DimZ": 3.0
      },
      "CampID": 4,
      "OverrideHintRange": 0.0,
      "CustomTriggerMap": {},
      "DialogueGroups": [],
      "TalkDialogGroupIDList": [
        101019793
      ],
      "TalkChosenType": "loop",
      "ServerInteractVerificationIDList": []
    },
    {
      "ID": 300012,
      "PosX": -7.440000057220459,
      "PosY": 0.5176810026168823,
      "PosZ": 14.35200023651123,
      "Name": "Prop12",
      "RotY": 90.0,
      "PropID": 120,
      "IsOverrideInitLevelGraph": true,
      "Trigger": {
        "Shape": "Box",
        "Radius": 2.0,
        "DimX": 2.0,
        "DimY": 2.0,
        "DimZ": 3.0
      },
      "CampID": 4,
      "OverrideHintRange": 0.0,
      "CustomTriggerMap": {},
      "DialogueGroups": [],
      "TalkDialogGroupIDList": [
        101019793
      ],
      "TalkChosenType": "loop",
      "ServerInteractVerificationIDList": []
    }
  ],
  "DistrictList": [],
  "WaypointList": [],
  "PathwayList": [],
  "BattleAreaList": [],
  "NPCList": [],
  "CrowdList": [],
  "PedestrianList": []
}