{
  "OnInitSequece": [],
  "OnStartSequece": [
    {
      "TaskList": [
        {
          "$type": "RPG.GameCore.LevelPerformanceInitialize",
          "PerformanceType": "D",
          "AreaPrefabPath": "Story/Discussion/Mission/8031101/DS803110123.prefab",
          "CreateCharacterList": [
            {
              "CharacterUniqueName": "W4_Male_29_C00",
              "AvatarID": "NPC_W4_Male_29",
              "AreaName": "DS803110123.prefab",
              "OverrideReplaceMaterialKeyList": []
            },
            {
              "CharacterUniqueName": "Chimera_03_C00",
              "AvatarID": "NPC_Special_Chimera_03",
              "AreaName": "DS803110123.prefab",
              "OverrideReplaceMaterialKeyList": [],
              "DisableEmoGraph": true
            },
            {
              "CharacterUniqueName": "PlayerBoy_00_C00",
              "AvatarID": "NPC_Avatar_Lad_PlayerBoy_00",
              "AreaName": "DS803110123.prefab",
              "OverrideReplaceMaterialKeyList": []
            },
            {
              "CharacterUniqueName": "PlayerGirl_00_C00",
              "AvatarID": "NPC_Avatar_Miss_PlayerGirl_00",
              "AreaName": "DS803110123.prefab",
              "OverrideReplaceMaterialKeyList": []
            },
            {
              "CharacterUniqueName": "Hyacine_00_C00",
              "AvatarID": "NPC_Avatar_Girl_Hyacine_00",
              "AreaName": "DS803110123.prefab",
              "OverrideReplaceMaterialKeyList": []
            },
            {
              "CharacterUniqueName": "ChariotChimera_00_03_C00",
              "AvatarID": "NPC_Special_ChariotChimera_00_03",
              "AreaName": "DS803110123.prefab",
              "OverrideReplaceMaterialKeyList": []
            },
            {
              "CharacterUniqueName": "Chimera_00_C01",
              "AvatarID": "NPC_Special_Chimera_00",
              "AreaName": "DS803110123.prefab",
              "OverrideReplaceMaterialKeyList": [
                "NPC_Special_Chimera_00_02_Body_02",
                "NPC_Special_Chimera_00_00_Item_00"
              ],
              "DisableEmoGraph": true
            },
            {
              "CharacterUniqueName": "Chimera_00_C02",
              "AvatarID": "NPC_Special_Chimera_00",
              "AreaName": "DS803110123.prefab",
              "OverrideReplaceMaterialKeyList": [
                "NPC_Special_Chimera_00_00_Body_02",
                "NPC_Special_Chimera_00_00_Item_00"
              ],
              "DisableEmoGraph": true
            },
            {
              "CharacterUniqueName": "Chimera_00_C03",
              "AvatarID": "NPC_Special_Chimera_00",
              "AreaName": "DS803110123.prefab",
              "OverrideReplaceMaterialKeyList": [
                "NPC_Special_Chimera_00_03_Body_04",
                "NPC_Special_Chimera_00_00_Item_00"
              ],
              "DisableEmoGraph": true
            },
            {
              "CharacterUniqueName": "Chimera_00_C04",
              "AvatarID": "NPC_Special_Chimera_00",
              "AreaName": "DS803110123.prefab",
              "OverrideReplaceMaterialKeyList": [
                "NPC_Special_Chimera_00_00_Body_03",
                "NPC_Special_Chimera_00_00_Item_00"
              ],
              "DisableEmoGraph": true
            },
            {
              "CharacterUniqueName": "Prop_Chap04_Chariot_01_C00",
              "AvatarID": "Prop_Chap04_Chariot_01",
              "AreaName": "DS803110123.prefab",
              "OverrideReplaceMaterialKeyList": []
            }
          ],
          "CaptureNPCList": [],
          "HideNPC": true,
          "EntityVisiableList": [],
          "HideProp": true,
          "PropVisiableList": [],
          "HideLocalPlayer": true,
          "FirstCameraAnchor": "Camera0102",
          "StreamingSourcesInBlackMask": [],
          "StreamingSourcesAfterBlackMask": [],
          "MarkStreamingItems": [],
          "AudioStateList": []
        },
        {
          "$type": "RPG.GameCore.PlayTimeline",
          "TimelineName": "Story/Discussion/Mission/8031101/DS80311012301.playable",
          "Type": "Discussion"
        },
        {
          "$type": "RPG.GameCore.PlayOptionTalk",
          "OptionList": [
            {
              "$type": "RPG.GameCore.OptionTalkInfo",
              "TalkSentenceID": 803112404,
              "OptionIconType": "ChatContinueIcon",
              "TriggerCustomString": "TalkSentence_803112405"
            },
            {
              "$type": "RPG.GameCore.OptionTalkInfo",
              "TalkSentenceID": 803112406,
              "OptionIconType": "ChatContinueIcon",
              "TriggerCustomString": "TalkSentence_803112407"
            }
          ]
        }
      ]
    },
    {
      "TaskList": [
        {
          "$type": "RPG.GameCore.WaitCustomString",
          "CustomString": {
            "Value": "TalkSentence_803112405"
          }
        },
        {
          "$type": "RPG.GameCore.PlayTimeline",
          "TimelineName": "Story/Discussion/Mission/8031101/DS80311012302.playable",
          "Type": "Discussion"
        },
        {
          "$type": "RPG.GameCore.TriggerCustomString",
          "CustomString": {
            "Value": "TalkSentence_803112408"
          }
        }
      ]
    },
    {
      "TaskList": [
        {
          "$type": "RPG.GameCore.WaitCustomString",
          "CustomString": {
            "Value": "TalkSentence_803112407"
          }
        },
        {
          "$type": "RPG.GameCore.PlayTimeline",
          "TimelineName": "Story/Discussion/Mission/8031101/DS80311012303.playable",
          "Type": "Discussion"
        },
        {
          "$type": "RPG.GameCore.TriggerCustomString",
          "CustomString": {
            "Value": "TalkSentence_803112408"
          }
        }
      ]
    },
    {
      "TaskList": [
        {
          "$type": "RPG.GameCore.WaitCustomString",
          "CustomString": {
            "Value": "TalkSentence_803112408"
          }
        },
        {
          "$type": "RPG.GameCore.PlayTimeline",
          "TimelineName": "Story/Discussion/Mission/8031101/DS80311012304.playable",
          "Type": "Discussion"
        },
        {
          "$type": "RPG.GameCore.TriggerCustomString",
          "CustomString": {
            "Value": "Wait_Option_803110123_598"
          }
        }
      ]
    },
    {
      "IsLoop": true,
      "TaskList": [
        {
          "$type": "RPG.GameCore.WaitCustomString",
          "CustomString": {
            "Value": "Wait_Option_803110123_598"
          }
        },
        {
          "$type": "RPG.GameCore.PlayOptionTalk",
          "OptionList": [
            {
              "$type": "RPG.GameCore.OptionTalkInfo",
              "TalkSentenceID": 803112410,
              "OptionIconType": "ChatLoopIcon",
              "TriggerCustomString": "TalkSentence_803112411"
            },
            {
              "$type": "RPG.GameCore.OptionTalkInfo",
              "TalkSentenceID": 803112413,
              "OptionIconType": "ChatLoopIcon",
              "TriggerCustomString": "TalkSentence_803112414"
            },
            {
              "$type": "RPG.GameCore.OptionTalkInfo",
              "TalkSentenceID": 803112416,
              "OptionIconType": "ChatLoopIcon",
              "TriggerCustomString": "TalkSentence_803112417"
            },
            {
              "$type": "RPG.GameCore.OptionTalkInfo",
              "TalkSentenceID": 803112419,
              "OptionIconType": "ChatContinueIcon",
              "TriggerCustomString": "TalkSentence_803112420"
            }
          ],
          "HideSelected": true
        }
      ]
    },
    {
      "IsLoop": true,
      "TaskList": [
        {
          "$type": "RPG.GameCore.WaitCustomString",
          "CustomString": {
            "Value": "TalkSentence_803112411"
          }
        },
        {
          "$type": "RPG.GameCore.PlayTimeline",
          "TimelineName": "Story/Discussion/Mission/8031101/DS80311012305.playable",
          "Type": "Discussion"
        },
        {
          "$type": "RPG.GameCore.TriggerCustomString",
          "CustomString": {
            "Value": "Wait_Option_803110123_598"
          }
        }
      ]
    },
    {
      "IsLoop": true,
      "TaskList": [
        {
          "$type": "RPG.GameCore.WaitCustomString",
          "CustomString": {
            "Value": "TalkSentence_803112414"
          }
        },
        {
          "$type": "RPG.GameCore.PlayTimeline",
          "TimelineName": "Story/Discussion/Mission/8031101/DS80311012306.playable",
          "Type": "Discussion"
        },
        {
          "$type": "RPG.GameCore.TriggerCustomString",
          "CustomString": {
            "Value": "Wait_Option_803110123_598"
          }
        }
      ]
    },
    {
      "IsLoop": true,
      "TaskList": [
        {
          "$type": "RPG.GameCore.WaitCustomString",
          "CustomString": {
            "Value": "TalkSentence_803112417"
          }
        },
        {
          "$type": "RPG.GameCore.PlayTimeline",
          "TimelineName": "Story/Discussion/Mission/8031101/DS80311012307.playable",
          "Type": "Discussion"
        },
        {
          "$type": "RPG.GameCore.TriggerCustomString",
          "CustomString": {
            "Value": "Wait_Option_803110123_598"
          }
        }
      ]
    },
    {
      "TaskList": [
        {
          "$type": "RPG.GameCore.WaitCustomString",
          "CustomString": {
            "Value": "TalkSentence_803112420"
          }
        },
        {
          "$type": "RPG.GameCore.PlayTimeline",
          "TimelineName": "Story/Discussion/Mission/8031101/DS80311012308.playable",
          "Type": "Discussion"
        },
        {
          "$type": "RPG.GameCore.PlayOptionTalk",
          "OptionList": [
            {
              "$type": "RPG.GameCore.OptionTalkInfo",
              "TalkSentenceID": 803112424,
              "OptionIconType": "ChatContinueIcon",
              "TriggerCustomString": "TalkSentence_803112425"
            },
            {
              "$type": "RPG.GameCore.OptionTalkInfo",
              "TalkSentenceID": 803112426,
              "OptionIconType": "ChatContinueIcon",
              "TriggerCustomString": "TalkSentence_803112427"
            }
          ]
        }
      ]
    },
    {
      "TaskList": [
        {
          "$type": "RPG.GameCore.WaitCustomString",
          "CustomString": {
            "Value": "TalkSentence_803112425"
          }
        },
        {
          "$type": "RPG.GameCore.PlayTimeline",
          "TimelineName": "Story/Discussion/Mission/8031101/DS80311012309.playable",
          "Type": "Discussion"
        },
        {
          "$type": "RPG.GameCore.TriggerCustomString",
          "CustomString": {
            "Value": "TalkSentence_803112428"
          }
        }
      ]
    },
    {
      "TaskList": [
        {
          "$type": "RPG.GameCore.WaitCustomString",
          "CustomString": {
            "Value": "TalkSentence_803112427"
          }
        },
        {
          "$type": "RPG.GameCore.PlayTimeline",
          "TimelineName": "Story/Discussion/Mission/8031101/DS80311012310.playable",
          "Type": "Discussion"
        },
        {
          "$type": "RPG.GameCore.TriggerCustomString",
          "CustomString": {
            "Value": "TalkSentence_803112428"
          }
        }
      ]
    },
    {
      "TaskList": [
        {
          "$type": "RPG.GameCore.WaitCustomString",
          "CustomString": {
            "Value": "TalkSentence_803112428"
          }
        },
        {
          "$type": "RPG.GameCore.PlayTimeline",
          "TimelineName": "Story/Discussion/Mission/8031101/DS80311012311.playable",
          "Type": "Discussion"
        },
        {
          "$type": "RPG.GameCore.PlayOptionTalk",
          "OptionList": [
            {
              "$type": "RPG.GameCore.OptionTalkInfo",
              "TalkSentenceID": 803112439,
              "OptionIconType": "ChatContinueIcon",
              "TriggerCustomString": "TalkSentence_803112440"
            },
            {
              "$type": "RPG.GameCore.OptionTalkInfo",
              "TalkSentenceID": 803112441,
              "OptionIconType": "ChatContinueIcon",
              "TriggerCustomString": "TalkSentence_803112442"
            }
          ]
        }
      ]
    },
    {
      "TaskList": [
        {
          "$type": "RPG.GameCore.WaitCustomString",
          "CustomString": {
            "Value": "TalkSentence_803112440"
          }
        },
        {
          "$type": "RPG.GameCore.PlayTimeline",
          "TimelineName": "Story/Discussion/Mission/8031101/DS80311012312.playable",
          "Type": "Discussion"
        },
        {
          "$type": "RPG.GameCore.TriggerCustomString",
          "CustomString": {
            "Value": "TalkSentence_803112442"
          }
        }
      ]
    },
    {
      "TaskList": [
        {
          "$type": "RPG.GameCore.WaitCustomString",
          "CustomString": {
            "Value": "TalkSentence_803112442"
          }
        },
        {
          "$type": "RPG.GameCore.PlayTimeline",
          "TimelineName": "Story/Discussion/Mission/8031101/DS80311012313.playable",
          "Type": "Discussion"
        },
        {
          "$type": "RPG.GameCore.EndPerformance"
        }
      ]
    },
    {
      "TaskList": [
        {
          "$type": "RPG.GameCore.WaitPerformanceEnd"
        },
        {
          "$type": "RPG.GameCore.FinishLevelGraph"
        }
      ]
    }
  ],
  "Type": "PerformanceD"
}