{
  "OnStartSequece": [
    {
      "TaskList": [
        {
          "$type": "RPG.GameCore.LevelPerformanceInitialize",
          "PerformanceType": "D",
          "AreaPrefabPath": "Story/Discussion/Mission/1040204/DS104020425.prefab",
          "CreateCharacterList": [
            {
              "CharacterUniqueName": "PlayerServant_30_C00",
              "AvatarID": "NPC_Servant_PlayerServant_30",
              "AreaName": "DS104020425.prefab"
            },
            {
              "CharacterUniqueName": "Castorice_00_C00",
              "AvatarID": "NPC_Avatar_Maid_Castorice_00",
              "AreaName": "DS104020425.prefab"
            },
            {
              "CharacterUniqueName": "PlayerBoy_00_C00",
              "AvatarID": "NPC_Avatar_Lad_PlayerBoy_00",
              "AreaName": "DS104020425.prefab"
            },
            {
              "CharacterUniqueName": "PlayerGirl_00_C00",
              "AvatarID": "NPC_Avatar_Miss_PlayerGirl_00",
              "AreaName": "DS104020425.prefab"
            }
          ],
          "CaptureNPCList": [],
          "HideNPC": true,
          "EntityVisiableList": [],
          "HideProp": true,
          "HideLocalPlayer": true,
          "FirstCameraAnchor": "Camera0404",
          "StreamingSourcesInBlackMask": [],
          "StreamingSourcesAfterBlackMask": [],
          "MarkStreamingItems": []
        },
        {
          "$type": "RPG.GameCore.PlayTimeline",
          "TimelineName": "Story/Discussion/Mission/1040204/DS10402042501.playable",
          "Type": "Discussion"
        },
        {
          "$type": "RPG.GameCore.PlayOptionTalk",
          "OptionList": [
            {
              "$type": "RPG.GameCore.OptionTalkInfo",
              "TalkSentenceID": 104024204,
              "OptionIconType": "ChatContinueIcon",
              "TriggerCustomString": "TalkSentence_104024205"
            }
          ]
        }
      ]
    },
    {
      "TaskList": [
        {
          "$type": "RPG.GameCore.WaitCustomString",
          "CustomString": {
            "Value": "TalkSentence_104024205"
          }
        },
        {
          "$type": "RPG.GameCore.PlayTimeline",
          "TimelineName": "Story/Discussion/Mission/1040204/DS10402042502.playable",
          "Type": "Discussion"
        },
        {
          "$type": "RPG.GameCore.TriggerCustomString",
          "CustomString": {
            "Value": "Wait_Option_104020425_666"
          }
        }
      ]
    },
    {
      "IsLoop": true,
      "TaskList": [
        {
          "$type": "RPG.GameCore.WaitCustomString",
          "CustomString": {
            "Value": "Wait_Option_104020425_666"
          }
        },
        {
          "$type": "RPG.GameCore.PlayOptionTalk",
          "OptionList": [
            {
              "$type": "RPG.GameCore.OptionTalkInfo",
              "TalkSentenceID": 104024206,
              "OptionIconType": "ChatLoopIcon",
              "TriggerCustomString": "TalkSentence_104024207"
            },
            {
              "$type": "RPG.GameCore.OptionTalkInfo",
              "TalkSentenceID": 104024208,
              "OptionIconType": "ChatLoopIcon",
              "TriggerCustomString": "TalkSentence_104024209"
            },
            {
              "$type": "RPG.GameCore.OptionTalkInfo",
              "TalkSentenceID": 104024212,
              "OptionIconType": "ChatLoopIcon",
              "TriggerCustomString": "TalkSentence_104024213"
            },
            {
              "$type": "RPG.GameCore.OptionTalkInfo",
              "TalkSentenceID": 104024214,
              "OptionIconType": "ChatLoopIcon",
              "TriggerCustomString": "TalkSentence_104024215"
            },
            {
              "$type": "RPG.GameCore.OptionTalkInfo",
              "TalkSentenceID": 104024217,
              "OptionIconType": "ChatContinueIcon",
              "TriggerCustomString": "TalkSentence_104024218"
            }
          ],
          "HideSelected": true
        }
      ]
    },
    {
      "IsLoop": true,
      "TaskList": [
        {
          "$type": "RPG.GameCore.WaitCustomString",
          "CustomString": {
            "Value": "TalkSentence_104024207"
          }
        },
        {
          "$type": "RPG.GameCore.PlayTimeline",
          "TimelineName": "Story/Discussion/Mission/1040204/DS10402042503.playable",
          "Type": "Discussion"
        },
        {
          "$type": "RPG.GameCore.TriggerCustomString",
          "CustomString": {
            "Value": "Wait_Option_104020425_666"
          }
        }
      ]
    },
    {
      "IsLoop": true,
      "TaskList": [
        {
          "$type": "RPG.GameCore.WaitCustomString",
          "CustomString": {
            "Value": "TalkSentence_104024209"
          }
        },
        {
          "$type": "RPG.GameCore.PlayTimeline",
          "TimelineName": "Story/Discussion/Mission/1040204/DS10402042504.playable",
          "Type": "Discussion"
        },
        {
          "$type": "RPG.GameCore.TriggerCustomString",
          "CustomString": {
            "Value": "Wait_Option_104020425_666"
          }
        }
      ]
    },
    {
      "IsLoop": true,
      "TaskList": [
        {
          "$type": "RPG.GameCore.WaitCustomString",
          "CustomString": {
            "Value": "TalkSentence_104024213"
          }
        },
        {
          "$type": "RPG.GameCore.PlayTimeline",
          "TimelineName": "Story/Discussion/Mission/1040204/DS10402042505.playable",
          "Type": "Discussion"
        },
        {
          "$type": "RPG.GameCore.TriggerCustomString",
          "CustomString": {
            "Value": "Wait_Option_104020425_666"
          }
        }
      ]
    },
    {
      "IsLoop": true,
      "TaskList": [
        {
          "$type": "RPG.GameCore.WaitCustomString",
          "CustomString": {
            "Value": "TalkSentence_104024215"
          }
        },
        {
          "$type": "RPG.GameCore.PlayTimeline",
          "TimelineName": "Story/Discussion/Mission/1040204/DS10402042506.playable",
          "Type": "Discussion"
        },
        {
          "$type": "RPG.GameCore.TriggerCustomString",
          "CustomString": {
            "Value": "Wait_Option_104020425_666"
          }
        }
      ]
    },
    {
      "IsLoop": true,
      "TaskList": [
        {
          "$type": "RPG.GameCore.WaitCustomString",
          "CustomString": {
            "Value": "TalkSentence_104024218"
          }
        },
        {
          "$type": "RPG.GameCore.PlayTimeline",
          "TimelineName": "Story/Discussion/Mission/1040204/DS10402042507.playable",
          "Type": "Discussion"
        },
        {
          "$type": "RPG.GameCore.PlayTimeline",
          "TimelineName": "Story/Discussion/Mission/1040204/DS10402042508.playable",
          "Type": "Discussion"
        },
        {
          "$type": "RPG.GameCore.EndPerformance"
        }
      ]
    },
    {
      "TaskList": [
        {
          "$type": "RPG.GameCore.WaitPerformanceEnd"
        },
        {
          "$type": "RPG.GameCore.FinishLevelGraph"
        }
      ]
    }
  ],
  "Type": "PerformanceD"
}